TensorFrost/TensorFrost.cpython-39-x86_64-linux-gnu.so
TensorFrost/__init__.py
TensorFrost/clipping.py
TensorFrost/default.py
TensorFrost/libglad_gl_core_46.so
TensorFrost/libglad_vulkan_12.a
TensorFrost/libglfw3.a
TensorFrost/optimizers.py
TensorFrost/random.py
TensorFrost/regularizers.py
TensorFrost/sort.py
include/GLFW/glfw3.h
include/GLFW/glfw3native.h
lib64/libglfw3.a
lib64/cmake/glfw3/glfw3Config.cmake
lib64/cmake/glfw3/glfw3ConfigVersion.cmake
lib64/cmake/glfw3/glfw3Targets-release.cmake
lib64/cmake/glfw3/glfw3Targets.cmake
lib64/pkgconfig/glfw3.pc
tensorfrost.libs/libglad_gl_core_46-0ef7cd3e.so
tensorfrost-0.7.4.dist-info/METADATA
tensorfrost-0.7.4.dist-info/WHEEL
tensorfrost-0.7.4.dist-info/RECORD
